tests/__init__.py
tests/test_tropoform.py
tests/fixtures/sample_tropo_module.py
tropoform/__init__.py
tropoform/tropoform.py
tropoform-0.3.8.dist-info/METADATA
tropoform-0.3.8.dist-info/WHEEL
tropoform-0.3.8.dist-info/entry_points.txt
tropoform-0.3.8.dist-info/top_level.txt
tropoform-0.3.8.dist-info/RECORD
