Metadata-Version: 2.1
Name: tropoform
Version: 0.3.8
Summary: A Terraform like utility for managing AWS Cloud Formation Stacks with troposphere
Home-page: https://github.com/cloudshiftstrategies/tropoform
Author: Brian Peterson
Author-email: brian.peterson@cloudshift.cc
License: UNKNOWN
Platform: UNKNOWN
Classifier: Programming Language :: Python :: 3
Classifier: License :: OSI Approved :: MIT License
Classifier: Operating System :: OS Independent
Requires-Python: >=3
Requires-Dist: boto3
Requires-Dist: botocore
Requires-Dist: troposphere
Requires-Dist: awacs
Requires-Dist: PyYAML
Requires-Dist: colorlog
